sqlmypy.py
sqltyping.py
sqlalchemy-stubs/__init__.pyi
sqlalchemy-stubs/events.pyi
sqlalchemy-stubs/exc.pyi
sqlalchemy-stubs/inspection.pyi
sqlalchemy-stubs/interfaces.pyi
sqlalchemy-stubs/log.pyi
sqlalchemy-stubs/pool.pyi
sqlalchemy-stubs/processors.pyi
sqlalchemy-stubs/schema.pyi
sqlalchemy-stubs/types.pyi
sqlalchemy-stubs/connectors/__init__.pyi
sqlalchemy-stubs/databases/__init__.pyi
sqlalchemy-stubs/dialects/__init__.pyi
sqlalchemy-stubs/dialects/firebird/__init__.pyi
sqlalchemy-stubs/dialects/mssql/__init__.pyi
sqlalchemy-stubs/dialects/mssql/base.pyi
sqlalchemy-stubs/dialects/mysql/__init__.pyi
sqlalchemy-stubs/dialects/mysql/base.pyi
sqlalchemy-stubs/dialects/mysql/cymysql.pyi
sqlalchemy-stubs/dialects/mysql/enumerated.pyi
sqlalchemy-stubs/dialects/mysql/gaerdbms.pyi
sqlalchemy-stubs/dialects/mysql/json.pyi
sqlalchemy-stubs/dialects/mysql/mysqlconnector.pyi
sqlalchemy-stubs/dialects/mysql/mysqldb.pyi
sqlalchemy-stubs/dialects/mysql/oursql.pyi
sqlalchemy-stubs/dialects/mysql/pymysql.pyi
sqlalchemy-stubs/dialects/mysql/pyodbc.pyi
sqlalchemy-stubs/dialects/mysql/reflection.pyi
sqlalchemy-stubs/dialects/mysql/types.pyi
sqlalchemy-stubs/dialects/mysql/zxjdbc.pyi
sqlalchemy-stubs/dialects/oracle/__init__.pyi
sqlalchemy-stubs/dialects/postgresql/__init__.pyi
sqlalchemy-stubs/dialects/postgresql/array.pyi
sqlalchemy-stubs/dialects/postgresql/base.pyi
sqlalchemy-stubs/dialects/postgresql/dml.pyi
sqlalchemy-stubs/dialects/postgresql/ext.pyi
sqlalchemy-stubs/dialects/postgresql/hstore.pyi
sqlalchemy-stubs/dialects/postgresql/json.pyi
sqlalchemy-stubs/dialects/postgresql/ranges.pyi
sqlalchemy-stubs/dialects/sqlite/__init__.pyi
sqlalchemy-stubs/dialects/sybase/__init__.pyi
sqlalchemy-stubs/engine/__init__.pyi
sqlalchemy-stubs/engine/base.pyi
sqlalchemy-stubs/engine/default.pyi
sqlalchemy-stubs/engine/interfaces.pyi
sqlalchemy-stubs/engine/reflection.pyi
sqlalchemy-stubs/engine/result.pyi
sqlalchemy-stubs/engine/strategies.pyi
sqlalchemy-stubs/engine/threadlocal.pyi
sqlalchemy_stubs-0.3.dist-info/LICENSE
sqlalchemy_stubs-0.3.dist-info/METADATA
sqlalchemy_stubs-0.3.dist-info/WHEEL
sqlalchemy_stubs-0.3.dist-info/top_level.txt
sqlalchemy_stubs-0.3.dist-info/RECORD
