Metadata-Version: 2.1
Name: sqlalchemy-stubs
Version: 0.3
Summary: SQLAlchemy stubs and mypy plugin
Home-page: https://github.com/dropbox/sqlalchemy-stubs
Author: Ivan Levkivskyi
Author-email: levkivskyi@gmail.com
License: MIT License
Platform: UNKNOWN
Classifier: Development Status :: 3 - Alpha
Classifier: Programming Language :: Python :: 3
